Workbook

Sheet Dashboard
A1: HECHOS DE KALDOR — TAIWÁN (1951–2050)
A7: INDICADORES CLAVE — TAIWÁN 2023
A8: 1952 | B8: 1954 | C8: 1954 | D8: 1953 | E8: 1953 | F8: 1976
A9: =_xlfn.XLOOKUP(A8,'Datos Raw'!$B$3:$B$75,'Datos Raw'!C3:C75) -> 6009.5031 | B9: =_xlfn.XLOOKUP(B8,'Datos Raw'!$B$3:$B$75,'Datos Raw'!D3:D75) -> 17672.282 | C9: =_xlfn.XLOOKUP(C8,'Datos Raw'!$B$3:$B$75,'Datos Raw'!E3:E75) -> 2.6060536 | D9: =_xlfn.XLOOKUP(D8,'Datos Raw'!$B$3:$B$75,'Datos Raw'!F3:F75) -> 0.74627417 | E9: =_xlfn.XLOOKUP(E8,'Datos Raw'!$B$3:$B$75,'Datos Raw'!G3:G75) -> 0.094873966 | F9: =_xlfn.XLOOKUP(F8,'Datos Raw'!$B$3:$B$75,'Datos Raw'!H3:H75) -> 20337.523
A10: Y/L | B10: K/L | C10: K/Y | D10: Labsh | E10: IRR | F10: w 2023
A11: PIB por trabajador (USD 2021) | B11: Capital por trabajador (USD 2021) | C11: Relacion capital-producto | D11: Participacion del trabajo | E11: Tasa interna de retorno | F11: Salario real (USD 2021)
A13: RESUMEN DE LOS SEIS HECHOS DE KALDOR
A14: Hecho | B14: Indicador | D14: Hoja de Detalle | E14: Crec. Anual
A15: H1 | B15: Y/L: Producto por Trabajador | D15: H1-PIB por L | E15: +4.45%/año
A16: H2 | B16: K/L: Capital por Trabajador | D16: H2-Capital por L | E16: +4.83%/año
A17: H3 | B17: K/Y: Relacion Capital-Producto | D17: H3-K sobre Y | E17: +0.38%/año
A18: H4 | B18: Labsh: Participacion del Trabajo | D18: H4-Labsh | E18: 0.00%/año
A19: H5 | B19: R: Tasa de Retorno del Capital | D19: H5-Retorno | E19: -0.38%/año
A20: H6 | B20: w: Salarios Reales | D20: H6-Salarios | E20: +4.45%/año
A23: Fuente: Penn World Tables v11.0 | Feenstra, Inklaar & Timmer (2015) |

Sheet H1-PIB por L
A1: HECHO 1 — Producto por Trabajador (Y/L) | H1: CRECIMIENTO | I1: =LN(B79/B7)/72 -> 0.044499644
A2: PIB real por trabajador — Penn World Tables v11.0
A3: Crecimiento promedio anual: +4.45%
A4: Definicion: El producto por trabajador crece a tasa constante a largo plazo y no se estanca.
A6: Año | B6: Y/L Real (USD 2021) | C6: Ln Y/L | D6: Ln Y/L proyección | E6: Tendencia | F6: Ln tendencia
A7: 1951 | B7: 5267.1358 | C7: =LN(B7) -> 8.569242 | E7: 5267.1358 | F7: =LN(E7) -> 8.569242
A8: 1952 | B8: 6009.5031 | C8: =LN(B8) -> 8.7010973 | E8: =E7*(1+$I$1) -> 5501.5215 | F8: =LN(E8) -> 8.61278
A9: 1953 | B9: 6465.4514 | C9: =LN(B9) -> 8.7742281 | E9: =E8*(1+$I$1) -> 5746.3372 | F9: =LN(E9) -> 8.6563179
A10: 1954 | B10: 6781.2429 | C10: =LN(B10) -> 8.8219157 | E10: =E9*(1+$I$1) -> 6002.0472 | F10: =LN(E10) -> 8.6998559
A11: 1955 | B11: 7101.6132 | C11: =LN(B11) -> 8.8680773 | E11: =E10*(1+$I$1) -> 6269.1362 | F11: =LN(E11) -> 8.7433939
A12: 1956 | B12: 7349.741 | C12: =LN(B12) -> 8.9024204 | E12: =E11*(1+$I$1) -> 6548.1105 | F12: =LN(E12) -> 8.7869318
A13: 1957 | B13: 7803.9798 | C13: =LN(B13) -> 8.9623891 | E13: =E12*(1+$I$1) -> 6839.4991 | F13: =LN(E13) -> 8.8304698
A14: 1958 | B14: 8135.9575 | C14: =LN(B14) -> 9.0040487 | E14: =E13*(1+$I$1) -> 7143.8543 | F14: =LN(E14) -> 8.8740077
A15: 1959 | B15: 8487.8081 | C15: =LN(B15) -> 9.0463861 | E15: =E14*(1+$I$1) -> 7461.7533 | F15: =LN(E15) -> 8.9175457
A16: 1960 | B16: 8912.3843 | C16: =LN(B16) -> 9.0951971 | E16: =E15*(1+$I$1) -> 7793.7987 | F16: =LN(E16) -> 8.9610837
A17: 1961 | B17: 9394.3891 | C17: =LN(B17) -> 9.1478679 | E17: =E16*(1+$I$1) -> 8140.6199 | F17: =LN(E17) -> 9.0046216
A18: 1962 | B18: 9889.8925 | C18: =LN(B18) -> 9.1992686 | E18: =E17*(1+$I$1) -> 8502.8746 | F18: =LN(E18) -> 9.0481596
A19: 1963 | B19: 10782.338 | C19: =LN(B19) -> 9.2856647 | E19: =E18*(1+$I$1) -> 8881.2495 | F19: =LN(E19) -> 9.0916975
... A78: 2022 | B78: 126979.18 | C78: =LN(B78) -> 11.751778 | E78: =E77*(1+$I$1) -> 115894.69 | F78: =LN(E78) -> 11.660437
A79: 2023 | B79: 129730.74 | C79: =LN(B79) -> 11.773216 | D79: 11.773216 | E79: =E78*(1+$I$1) -> 121051.96 | F79: =LN(E79) -> 11.703975
A80: 2024 | B80: =B79*(1+$I$1) -> 135503.71 | D80: =LN(B80) -> 11.816754 | E80: =E79*(1+$I$1) -> 126438.73 | F80: 11.816754
A81: 2025 | B81: =B80*(1+$I$1) -> 141533.58 | D81: =LN(B81) -> 11.860292 | E81: =E80*(1+$I$1) -> 132065.21 | F81: 11.860292
A82: 2026 | B82: =B81*(1+$I$1) -> 147831.77 | D82: =LN(B82) -> 11.90383 | E82: =E81*(1+$I$1) -> 137942.07 | F82: 11.90383
A83: 2027 | B83: =B82*(1+$I$1) -> 154410.23 | D83: =LN(B83) -> 11.947368 | E83: =E82*(1+$I$1) -> 144080.44 | F83: 11.947368
A84: 2028 | B84: =B83*(1+$I$1) -> 161281.43 | D84: =LN(B84) -> 11.990906 | E84: =E83*(1+$I$1) -> 150491.97 | F84: 11.990906
A85: 2029 | B85: =B84*(1+$I$1) -> 168458.4 | D85: =LN(B85) -> 12.034444 | E85: =E84*(1+$I$1) -> 157188.81 | F85: 12.034444
A86: 2030 | B86: =B85*(1+$I$1) -> 175954.74 | D86: =LN(B86) -> 12.077982 | E86: =E85*(1+$I$1) -> 164183.65 | F86: 12.077982
A87: 2031 | B87: =B86*(1+$I$1) -> 183784.66 | D87: =LN(B87) -> 12.12152 | E87: =E86*(1+$I$1) -> 171489.77 | F87: 12.12152
A88: 2032 | B88: =B87*(1+$I$1) -> 191963.01 | D88: =LN(B88) -> 12.165058 | E88: =E87*(1+$I$1) -> 179121 | F88: 12.165058
A89: 2033 | B89: =B88*(1+$I$1) -> 200505.3 | D89: =LN(B89) -> 12.208596 | E89: =E88*(1+$I$1) -> 187091.82 | F89: 12.208596
A90: 2034 | B90: =B89*(1+$I$1) -> 209427.71 | D90: =LN(B90) -> 12.252134 | E90: =E89*(1+$I$1) -> 195417.34 | F90: 12.252134
A91: 2035 | B91: =B90*(1+$I$1) -> 218747.17 | D91: =LN(B91) -> 12.295672 | E91: =E90*(1+$I$1) -> 204113.34 | F91: 12.295672
... A106: 2050 | B106: =B105*(1+$I$1) -> 420307.26 | D106: =LN(B106) -> 12.948741 | E106: =E105*(1+$I$1) -> 392189.39 | F106: 12.948741
A108: Fuente: Penn World Tables v11.0 | Feenstra, Inklaar & Timmer (2015) | Elaboracion propia

Sheet H2-Capital por L
A1: HECHO 2 — Capital por Trabajador (K/L) | H1: CRECIMIENTO | I1: =LN(B79/B7)/72 -> 0.04826701
A2: Stock de capital real por trabajador — Penn World Tables v11.0
A3: Crecimiento promedio anual: +4.83%
A4: Definicion: El stock de capital disponible para cada trabajador aumenta a tasa estable a largo plazo.
A6: Año | B6: K/L Real (USD 2021) | C6: Ln K/Y Real | D6: Ln K/Y proyeccion | E6: Tendencia | F6: Ln tendencia
A7: 1951 | B7: 16807.807 | C7: =LN(B7) -> 9.7295988 | E7: 16807.807 | F7: =LN(E7) -> 9.7295988
A8: 1952 | B8: 16895.355 | C8: =LN(B8) -> 9.734794 | E8: =E7*(1+$I$1) -> 17619.07 | F8: =LN(E8) -> 9.7767371
A9: 1953 | B9: 17290.855 | C9: =LN(B9) -> 9.757933 | E9: =E8*(1+$I$1) -> 18469.49 | F9: =LN(E9) -> 9.8238754
A10: 1954 | B10: 17672.282 | C10: =LN(B10) -> 9.7797527 | E10: =E9*(1+$I$1) -> 19360.957 | F10: =LN(E10) -> 9.8710138
A11: 1955 | B11: 17780.63 | C11: =LN(B11) -> 9.785865 | E11: =E10*(1+$I$1) -> 20295.452 | F11: =LN(E11) -> 9.9181521
A12: 1956 | B12: 18087.594 | C12: =LN(B12) -> 9.8029816 | E12: =E11*(1+$I$1) -> 21275.053 | F12: =LN(E12) -> 9.9652904
A13: 1957 | B13: 18367.876 | C13: =LN(B13) -> 9.8183585 | E13: =E12*(1+$I$1) -> 22301.936 | F13: =LN(E13) -> 10.012429
A14: 1958 | B14: 18818.057 | C14: =LN(B14) -> 9.8425722 | E14: =E13*(1+$I$1) -> 23378.384 | F14: =LN(E14) -> 10.059567
A15: 1959 | B15: 19494.236 | C15: =LN(B15) -> 9.8778741 | E15: =E14*(1+$I$1) -> 24506.788 | F15: =LN(E15) -> 10.106705
A16: 1960 | B16: 20413.598 | C16: =LN(B16) -> 9.9239565 | E16: =E15*(1+$I$1) -> 25689.658 | F16: =LN(E16) -> 10.153844
A17: 1961 | B17: 21169.165 | C17: =LN(B17) -> 9.9603009 | E17: =E16*(1+$I$1) -> 26929.621 | F17: =LN(E17) -> 10.200982
A18: 1962 | B18: 21878.542 | C18: =LN(B18) -> 9.9932616 | E18: =E17*(1+$I$1) -> 28229.433 | F18: =LN(E18) -> 10.24812
A19: 1963 | B19: 22840.424 | C19: =LN(B19) -> 10.036287 | E19: =E18*(1+$I$1) -> 29591.983 | F19: =LN(E19) -> 10.295259
... A78: 2022 | B78: 528121.29 | C78: =LN(B78) -> 13.177081 | E78: =E77*(1+$I$1) -> 477548.24 | F78: =LN(E78) -> 13.07642
A79: 2023 | B79: 542977.66 | C79: =LN(B79) -> 13.204823 | D79: 13.204823 | E79: =E78*(1+$I$1) -> 500598.06 | F79: =LN(E79) -> 13.123559
A80: 2024 | B80: =B79*(1+$I$1) -> 569185.57 | D80: =LN(B80) -> 13.251962 | E80: =E79*(1+$I$1) -> 524760.44 | F80: =LN(E80) -> 13.170697
A81: 2025 | B81: =B80*(1+$I$1) -> 596658.46 | D81: =LN(B81) -> 13.2991 | E81: =E80*(1+$I$1) -> 550089.05 | F81: =LN(E81) -> 13.217835
A82: 2026 | B82: =B81*(1+$I$1) -> 625457.38 | D82: =LN(B82) -> 13.346238 | E82: =E81*(1+$I$1) -> 576640.21 | F82: =LN(E82) -> 13.264974
A83: 2027 | B83: =B82*(1+$I$1) -> 655646.33 | D83: =LN(B83) -> 13.393377 | E83: =E82*(1+$I$1) -> 604472.91 | F83: =LN(E83) -> 13.312112
A84: 2028 | B84: =B83*(1+$I$1) -> 687292.42 | D84: =LN(B84) -> 13.440515 | E84: =E83*(1+$I$1) -> 633649 | F84: =LN(E84) -> 13.35925
A85: 2029 | B85: =B84*(1+$I$1) -> 720465.97 | D85: =LN(B85) -> 13.487653 | E85: =E84*(1+$I$1) -> 664233.35 | F85: =LN(E85) -> 13.406389
A86: 2030 | B86: =B85*(1+$I$1) -> 755240.71 | D86: =LN(B86) -> 13.534792 | E86: =E85*(1+$I$1) -> 696293.9 | F86: =LN(E86) -> 13.453527
A87: 2031 | B87: =B86*(1+$I$1) -> 791693.92 | D87: =LN(B87) -> 13.58193 | E87: =E86*(1+$I$1) -> 729901.93 | F87: =LN(E87) -> 13.500665
A88: 2032 | B88: =B87*(1+$I$1) -> 829906.62 | D88: =LN(B88) -> 13.629068 | E88: =E87*(1+$I$1) -> 765132.11 | F88: =LN(E88) -> 13.547804
A89: 2033 | B89: =B88*(1+$I$1) -> 869963.73 | D89: =LN(B89) -> 13.676207 | E89: =E88*(1+$I$1) -> 802062.75 | F89: =LN(E89) -> 13.594942
A90: 2034 | B90: =B89*(1+$I$1) -> 911954.28 | D90: =LN(B90) -> 13.723345 | E90: =E89*(1+$I$1) -> 840775.92 | F90: =LN(E90) -> 13.64208
A91: 2035 | B91: =B90*(1+$I$1) -> 955971.58 | D91: =LN(B91) -> 13.770483 | E91: =E90*(1+$I$1) -> 881357.66 | F91: =LN(E91) -> 13.689219
... A106: 2050 | B106: =B105*(1+$I$1) -> 1938758.7 | D106: =LN(B106) -> 14.477558 | E106: =E105*(1+$I$1) -> 1787437.9 | F106: =LN(E106) -> 14.396294
A108: Fuente: Penn World Tables v11.0 | Feenstra, Inklaar & Timmer (2015) | Elaboracion propia

Sheet H3-K sobre Y
A1: HECHO 3 — Relacion Capital-Producto (K/Y) | E1: CRECIMIENTO | F1: =LN(B79/B7)/72 -> 0.003767366
A2: Ratio capital sobre PIB — Penn World Tables v11.0
A3: Crecimiento promedio anual: +0.38%
A4: Definicion: La relacion capital-producto crece a ritmo aproximadamente constante en largos periodos.
A6: Año | B6: K/Y (Ratio) | C6: Proyeccion 2024-2050
A7: 1951 | B7: 3.1910715
A8: 1952 | B8: 2.8114397
A9: 1953 | B9: 2.6743462
A10: 1954 | B10: 2.6060536
A11: 1955 | B11: 2.5037452
A12: 1956 | B12: 2.4609839
A13: 1957 | B13: 2.353655
A14: 1958 | B14: 2.3129493
A15: 1959 | B15: 2.2967339
A16: 1960 | B16: 2.2904755
A17: 1961 | B17: 2.2533839
A18: 1962 | B18: 2.2122123
... A78: 2022 | B78: 4.1591173
A79: 2023 | B79: 4.1854202 | C79: 4.1854202
A80: 2024 | C80: =C79*(1+$F$1) -> 4.2011882
A81: 2025 | C81: =C80*(1+$F$1) -> 4.2170157
A82: 2026 | C82: =C81*(1+$F$1) -> 4.2329027
A83: 2027 | C83: =C82*(1+$F$1) -> 4.2488496
A84: 2028 | C84: =C83*(1+$F$1) -> 4.2648566
A85: 2029 | C85: =C84*(1+$F$1) -> 4.2809238
A86: 2030 | C86: =C85*(1+$F$1) -> 4.2970516
A87: 2031 | C87: =C86*(1+$F$1) -> 4.3132402
A88: 2032 | C88: =C87*(1+$F$1) -> 4.3294898
A89: 2033 | C89: =C88*(1+$F$1) -> 4.3458005
A90: 2034 | C90: =C89*(1+$F$1) -> 4.3621728
A91: 2035 | C91: =C90*(1+$F$1) -> 4.3786067
... A106: 2050 | C106: =C105*(1+$F$1) -> 4.6326769
A108: Fuente: Penn World Tables v11.0 | Feenstra, Inklaar & Timmer (2015) | Elaboracion propia

Sheet H4-Labsh
A1: HECHO 4 — Participacion del Trabajo (Labsh) | E1: CRECIMIENTO | F1: =LN(B79/B7)/72 -> 0
A2: Participacion de la remuneracion laboral en el PIB — Penn World Tables v11.0
A3: Crecimiento promedio anual: +0.00% | Veredicto: Cumple
A4: Definicion: La participacion del trabajo en el ingreso tiende a permanecer estable a largo plazo.
A6: Año | B6: Labsh (%) | C6: Proyeccion 2024-2050
A7: 1951 | B7: 0.74627417
A8: 1952 | B8: 0.74627417
A9: 1953 | B9: 0.74627417
A10: 1954 | B10: 0.74627417
A11: 1955 | B11: 0.74627417
A12: 1956 | B12: 0.74627417
A13: 1957 | B13: 0.74627417
A14: 1958 | B14: 0.74627417
A15: 1959 | B15: 0.74627417
A16: 1960 | B16: 0.74627417
A17: 1961 | B17: 0.74627417
A18: 1962 | B18: 0.74627417
... A78: 2022 | B78: 0.74627417
A79: 2023 | B79: 0.74627417 | C79: 0.74627417
A80: 2024 | C80: 0.74627417
A81: 2025 | C81: 0.74627417
A82: 2026 | C82: 0.74627417
A83: 2027 | C83: 0.74627417
A84: 2028 | C84: 0.74627417
A85: 2029 | C85: 0.74627417
A86: 2030 | C86: 0.74627417
A87: 2031 | C87: 0.74627417
A88: 2032 | C88: 0.74627417
A89: 2033 | C89: 0.74627417
A90: 2034 | C90: 0.74627417
A91: 2035 | C91: 0.74627417
... A106: 2050 | C106: 0.74627417
A108: Fuente: Penn World Tables v11.0 | Feenstra, Inklaar & Timmer (2015) | Elaboracion propia

Sheet H5-Retorno
A1: HECHO 5 — Tasa de Retorno del Capital (R) | E1: CRECIMIENTO | F1: =LN(B79/B7)/72 -> -0.003767366
A2: Internal rate of return del capital — Penn World Tables v11.0
A3: Crecimiento promedio anual: -0.38%
A4: Definicion: La tasa de retorno del capital es relativamente constante a largo plazo.
A6: Año | B6: IRR (Tasa Retorno) | C6: Proyeccion 2024-2050
A7: 1951 | B7: 0.079511169
A8: 1952 | B8: 0.090247652
A9: 1953 | B9: 0.094873966
A10: 1954 | B10: 0.097360173
A11: 1955 | B11: 0.10133852
A12: 1956 | B12: 0.10309934
A13: 1957 | B13: 0.10780077
A14: 1958 | B14: 0.10969796
A15: 1959 | B15: 0.11047245
A16: 1960 | B16: 0.1107743
A17: 1961 | B17: 0.11259769
A18: 1962 | B18: 0.11469326
... A78: 2022 | B78: 0.06100473
A79: 2023 | B79: 0.06062135 | C79: 0.06062135
A80: 2024 | C80: =C79+(1*$F$1) -> 0.056853984
A81: 2025 | C81: =C80+(1*$F$1) -> 0.053086618
A82: 2026 | C82: =C81+(1*$F$1) -> 0.049319252
A83: 2027 | C83: =C82+(1*$F$1) -> 0.045551886
A84: 2028 | C84: =C83+(1*$F$1) -> 0.04178452
A85: 2029 | C85: =C84+(1*$F$1) -> 0.038017154
A86: 2030 | C86: =C85+(1*$F$1) -> 0.034249788
A87: 2031 | C87: =C86+(1*$F$1) -> 0.030482422
A88: 2032 | C88: =C87+(1*$F$1) -> 0.026715056
A89: 2033 | C89: =C88+(1*$F$1) -> 0.02294769
A90: 2034 | C90: =C89+(1*$F$1) -> 0.019180324
A91: 2035 | C91: =C90+(1*$F$1) -> 0.015412958
... A106: 2050 | C106: =C105+(1*$F$1) -> -0.041097532
A108: Fuente: Penn World Tables v11.0 | Feenstra, Inklaar & Timmer (2015) | Elaboracion propia

Sheet H6-Salarios
A1: HECHO 6 — Salarios Reales (w) | H1: CRECIMIENTO | I1: =LN(B79/B7)/72 -> 0.044499644
A2: Salario real por trabajador — Penn World Tables v11.0
A3: Crecimiento promedio anual: +4.45%
A4: Definicion: Los salarios reales crecen a una tasa sostenida a lo largo del tiempo.
A6: Año | B6: Salario Real (USD 2021) | C6: Ln Salarios empiricos | D6: Ln proyeccion | E6: Tendencia | F6: Ln tendencia
A7: 1951 | B7: 3930.7274 | C7: =LN(B7) -> 8.2765798 | E7: 3930.7274 | F7: =LN(E7) -> 8.2765798
A8: 1952 | B8: 4484.737 | C8: =LN(B8) -> 8.4084351 | E8: =E7*(1+$I$1) -> 4105.6434 | F8: =LN(E8) -> 8.3201177
A9: 1953 | B9: 4824.9994 | C9: =LN(B9) -> 8.4815659 | E9: =E8*(1+$I$1) -> 4288.3431 | F9: =LN(E9) -> 8.3636557
A10: 1954 | B10: 5060.6664 | C10: =LN(B10) -> 8.5292535 | E10: =E9*(1+$I$1) -> 4479.1728 | F10: =LN(E10) -> 8.4071937
A11: 1955 | B11: 5299.7506 | C11: =LN(B11) -> 8.575415 | E11: =E10*(1+$I$1) -> 4678.4944 | F11: =LN(E11) -> 8.4507316
A12: 1956 | B12: 5484.9219 | C12: =LN(B12) -> 8.6097581 | E12: =E11*(1+$I$1) -> 4886.6857 | F12: =LN(E12) -> 8.4942696
A13: 1957 | B13: 5823.9086 | C13: =LN(B13) -> 8.6697269 | E13: =E12*(1+$I$1) -> 5104.1415 | F13: =LN(E13) -> 8.5378076
A14: 1958 | B14: 6071.6549 | C14: =LN(B14) -> 8.7113865 | E14: =E13*(1+$I$1) -> 5331.274 | F14: =LN(E14) -> 8.5813455
A15: 1959 | B15: 6334.2319 | C15: =LN(B15) -> 8.7537238 | E15: =E14*(1+$I$1) -> 5568.5138 | F15: =LN(E15) -> 8.6248835
A16: 1960 | B16: 6651.0822 | C16: =LN(B16) -> 8.8025349 | E16: =E15*(1+$I$1) -> 5816.3107 | F16: =LN(E16) -> 8.6684214
A17: 1961 | B17: 7010.7899 | C17: =LN(B17) -> 8.8552057 | E17: =E16*(1+$I$1) -> 6075.1344 | F17: =LN(E17) -> 8.7119594
A18: 1962 | B18: 7380.5714 | C18: =LN(B18) -> 8.9066063 | E18: =E17*(1+$I$1) -> 6345.4757 | F18: =LN(E18) -> 8.7554974
A19: 1963 | B19: 8046.5803 | C19: =LN(B19) -> 8.9930025 | E19: =E18*(1+$I$1) -> 6627.8471 | F19: =LN(E19) -> 8.7990353
... A78: 2022 | B78: 94761.28 | C78: =LN(B78) -> 11.459116 | E78: =E77*(1+$I$1) -> 86489.215 | F78: =LN(E78) -> 11.367775
A79: 2023 | B79: 96814.701 | C79: =LN(B79) -> 11.480554 | D79: 11.480554 | E79: =E78*(1+$I$1) -> 90337.954 | F79: =LN(E79) -> 11.411313
A80: 2024 | B80: =B79*(1+$I$1) -> 101122.92 | D80: =LN(B80) -> 11.524092 | E80: =E79*(1+$I$1) -> 94357.961 | F80: =LN(E80) -> 11.454851
A81: 2025 | B81: =B80*(1+$I$1) -> 105622.85 | D81: =LN(B81) -> 11.56763 | E81: =E80*(1+$I$1) -> 98556.857 | F81: =LN(E81) -> 11.498389
A82: 2026 | B82: =B81*(1+$I$1) -> 110323.03 | D82: =LN(B82) -> 11.611168 | E82: =E81*(1+$I$1) -> 102942.6 | F82: =LN(E82) -> 11.541927
A83: 2027 | B83: =B82*(1+$I$1) -> 115232.37 | D83: =LN(B83) -> 11.654706 | E83: =E82*(1+$I$1) -> 107523.51 | F83: =LN(E83) -> 11.585465
A84: 2028 | B84: =B83*(1+$I$1) -> 120360.17 | D84: =LN(B84) -> 11.698244 | E84: =E83*(1+$I$1) -> 112308.27 | F84: =LN(E84) -> 11.629003
A85: 2029 | B85: =B84*(1+$I$1) -> 125716.15 | D85: =LN(B85) -> 11.741782 | E85: =E84*(1+$I$1) -> 117305.95 | F85: =LN(E85) -> 11.672541
A86: 2030 | B86: =B85*(1+$I$1) -> 131310.48 | D86: =LN(B86) -> 11.78532 | E86: =E85*(1+$I$1) -> 122526.02 | F86: =LN(E86) -> 11.716079
A87: 2031 | B87: =B86*(1+$I$1) -> 137153.75 | D87: =LN(B87) -> 11.828858 | E87: =E86*(1+$I$1) -> 127978.38 | F87: =LN(E87) -> 11.759617
A88: 2032 | B88: =B87*(1+$I$1) -> 143257.04 | D88: =LN(B88) -> 11.872396 | E88: =E87*(1+$I$1) -> 133673.38 | F88: =LN(E88) -> 11.803155
A89: 2033 | B89: =B88*(1+$I$1) -> 149631.93 | D89: =LN(B89) -> 11.915934 | E89: =E88*(1+$I$1) -> 139621.79 | F89: =LN(E89) -> 11.846693
A90: 2034 | B90: =B89*(1+$I$1) -> 156290.49 | D90: =LN(B90) -> 11.959472 | E90: =E89*(1+$I$1) -> 145834.91 | F90: =LN(E90) -> 11.890231
A91: 2035 | B91: =B90*(1+$I$1) -> 163245.37 | D91: =LN(B91) -> 12.00301 | E91: =E90*(1+$I$1) -> 152324.52 | F91: =LN(E91) -> 11.933768
... A106: 2050 | B106: =B105*(1+$I$1) -> 313664.45 | D106: =LN(B106) -> 12.656079 | E106: =E105*(1+$I$1) -> 292680.81 | F106: =LN(E106) -> 12.586838
A108: Fuente: Penn World Tables v11.0 | Feenstra, Inklaar & Timmer (2015) | Elaboracion propia

Sheet Datos Raw
B2: Año | C2: Y/L (USD) | D2: K/L (USD) | E2: K/Y | F2: Labsh | G2: IRR | H2: Salario (USD)
B3: 1951 | C3: 5267.1358 | D3: 16807.807 | E3: 3.1910715 | F3: 0.74627417 | G3: 0.079511169 | H3: 3930.7274
B4: 1952 | C4: 6009.5031 | D4: 16895.355 | E4: 2.8114397 | F4: 0.74627417 | G4: 0.090247652 | H4: 4484.737
B5: 1953 | C5: 6465.4514 | D5: 17290.855 | E5: 2.6743462 | F5: 0.74627417 | G5: 0.094873966 | H5: 4824.9994
B6: 1954 | C6: 6781.2429 | D6: 17672.282 | E6: 2.6060536 | F6: 0.74627417 | G6: 0.097360173 | H6: 5060.6664
B7: 1955 | C7: 7101.6132 | D7: 17780.63 | E7: 2.5037452 | F7: 0.74627417 | G7: 0.10133852 | H7: 5299.7506
B8: 1956 | C8: 7349.741 | D8: 18087.594 | E8: 2.4609839 | F8: 0.74627417 | G8: 0.10309934 | H8: 5484.9219
B9: 1957 | C9: 7803.9798 | D9: 18367.876 | E9: 2.353655 | F9: 0.74627417 | G9: 0.10780077 | H9: 5823.9086
B10: 1958 | C10: 8135.9575 | D10: 18818.057 | E10: 2.3129493 | F10: 0.74627417 | G10: 0.10969796 | H10: 6071.6549
B11: 1959 | C11: 8487.8081 | D11: 19494.236 | E11: 2.2967339 | F11: 0.74627417 | G11: 0.11047245 | H11: 6334.2319
B12: 1960 | C12: 8912.3843 | D12: 20413.598 | E12: 2.2904755 | F12: 0.74627417 | G12: 0.1107743 | H12: 6651.0822
B13: 1961 | C13: 9394.3891 | D13: 21169.165 | E13: 2.2533839 | F13: 0.74627417 | G13: 0.11259769 | H13: 7010.7899
B14: 1962 | C14: 9889.8925 | D14: 21878.542 | E14: 2.2122123 | F14: 0.74627417 | G14: 0.11469326 | H14: 7380.5714
... B75: 2023 | C75: 129730.74 | D75: 542977.66 | E75: 4.1854202 | F75: 0.74627417 | G75: 0.06062135 | H75: 96814.701
B76: Fuente: Penn World Tables v11.0 | Feenstra, Inklaar & Timmer (2015)

Sheet Metodologia
A1: METODOLOGIA Y FUENTES
A2: Hechos de Kaldor — Taiwan 1951-2023 con proyecciones hasta 2050
A4: Variable | B4: Formula o Definicion | C4: Fuente
A5: Y/L — PIB por Trabajador | B5: rgdpe / emp | C5: rgdpe, emp — Penn World Tables v11.0
A6: K/L — Capital por Trabajador | B6: rnna / emp | C6: rnna, emp — Penn World Tables v11.0
A7: K/Y — Relacion Capital-Producto | B7: rnna / rgdpe | C7: rnna, rgdpe — Penn World Tables v11.0
A8: Labsh — Participacion del Trabajo | B8: labsh (variable directa) | C8: labsh — Penn World Tables v11.0
A9: R — Tasa de Retorno | B9: (1-labsh) x rgdpe / rnna | C9: rgdpe, rnna, labsh — Penn World Tables v11.0
A10: w — Salarios Reales | B10: labsh x rgdpe / emp | C10: rgdpe, labsh, emp — Penn World Tables v11.0
A11: Tendencia | B11: Regresion exponencial sobre Ln(variable) | C11: Elaboracion propia
A12: Proyeccion 2024-2050 | B12: Extrapolacion tasa de crecimiento promedio | C12: Elaboracion propia
A13: Pais analizado | B13: Taiwan (TWN) | C13: Penn World Tables v11.0
A14: Periodo historico | B14: 1951 — 2023 | C14: Penn World Tables v11.0
A15: Periodo proyectado | B15: 2024 — 2050 | C15: Elaboracion propia
... A17: URL base de datos | B17: www.ggdc.net/pwt | C17: Penn World Tables v11.0
